{
    "version": "1.7.10",
    "architecture": {
        "32bit": {
            "url": "https://github.com/xavidop/dialogflow-cx-cli/releases/download/v1.7.10/cxcli_Windows_i386.zip",
            "bin": [
                "cxcli.exe"
            ],
            "hash": "fcb9fc4e024b4ba938e0bf4b04c377756b90b86435ede0784593d1a878e2c8b3"
        },
        "64bit": {
            "url": "https://github.com/xavidop/dialogflow-cx-cli/releases/download/v1.7.10/cxcli_Windows_x86_64.zip",
            "bin": [
                "cxcli.exe"
            ],
            "hash": "538ee1b9bfae623766e8b55be615df8a68ead1c7e66eb3349ef7d96260a798dd"
        }
    },
    "homepage": "https://cxcli.xavidop.me",
    "license": "Apache-2.0",
    "description": "The missing CLI for your Dialogflow CX projects"
}